RISC-V-CPU/ALU.sv
module ALU #(
    parameter 
              DATA_WIDTH = 32
)(
    input logic [DATA_WIDTH-1:0] ALUop1,
    input logic ALUsrc,
    input logic [DATA_WIDTH-1:0] regOp2,
    input logic [DATA_WIDTH-1:0] ImmOp,
    input logic [2:0] ALUctrl,
    
    output logic [DATA_WIDTH-1:0] ALUout,
    output logic EQ

);
    logic [DATA_WIDTH-1:0] ALUop2;
    assign ALUop2 = ALUsrc ? ImmOp : regOp2;

    always_comb begin
    
        casez (ALUctrl)
           3'b000:  ALUout = ALUop1 + ALUop2;
       
           3'b001:  ALUout = 32'b0;

           3'b010:  ALUout = 32'b0;
           
           3'b011:  ALUout = 32'b0;

           3'b100:  ALUout = 32'b0;
           3'b110:  ALUout = 32'b0;
           3'b101:  ALUout = 32'b0;

           default: ALUout = 0;
    
        
         endcase
     end
     assign EQ =  (ALUop1 == ALUop2) ? 1:0;
    

endmodule

RISC-V-CPU/ram.sv
module ram #(
    parameter ADDRESS_WIDTH = 5,
              DATA_WIDTH = 32
)(
    input logic clk,
    input logic [ADDRESS_WIDTH-1:0] AD1,    
    input logic [ADDRESS_WIDTH-1:0] AD2,
    input logic [ADDRESS_WIDTH-1:0] AD3,

    input logic WE3,
    input logic [DATA_WIDTH-1:0] WD3,

    output logic [DATA_WIDTH-1:0] a0,
    output logic [DATA_WIDTH-1:0] RD1,
    output logic [DATA_WIDTH-1:0] RD2

);

    logic [DATA_WIDTH-1:0] ram_array [2**ADDRESS_WIDTH-1:0];
//assign ram_array[5'b00000] = {DATA_WIDTH{1'b0}};
    always_comb begin
        RD1 = ram_array[AD1];
        RD2 = ram_array [AD2];
    end

    initial begin
        for (int i = 0; i< $size(ram_array); i++) begin
            ram_array[i] = 32'b0;
        end
    end

    always_ff @ (posedge clk) begin
        if (WE3)  ram_array[AD3] <= WD3;
    end

    assign a0 = ram_array[10];

endmodule

RISC-V-CPU/red_top.sv
 module red_top #(
    parameter ADDRESS_WIDTH = 5,
              ALUctrl_WIDTH = 3,
              DATA_WIDTH = 32
)(
  input logic clk,
  // input logic [19:15] AD1,    
  // input logic [24:20] AD2,
  // input logic [11:7] AD3,

  input logic [DATA_WIDTH-1:0] ImmOp,
  input logic RegWrite,
  input logic [ALUctrl_WIDTH-1:0] ALUctrl,
  input logic ALUsrc,
  input logic [ADDRESS_WIDTH-1:0] rs1,
  input logic [ADDRESS_WIDTH-1:0] rs2,
  input logic [ADDRESS_WIDTH-1:0] rd,

  output logic  EQ,
  output logic [DATA_WIDTH-1:0] a0

);
  
   logic [DATA_WIDTH-1:0] ALUop1;
   logic [DATA_WIDTH-1:0] regOp2;
   logic [DATA_WIDTH-1:0] ALUout;

  //  logic [DATA_WIDTH-1:0] RD2;
  //  logic [ADDRESS_WIDTH-1:0] AD2;
  
ram ram (
  .clk (clk),
  .AD1 (rs1),
  .AD2 (rs2),
  .AD3 (rd),
  .WE3 (RegWrite),
  .WD3 (ALUout),
  .a0 (a0),
  .RD1 (ALUop1),
  .RD2 (regOp2)
);

ALU ALU (
   .ALUop1 (ALUop1),
   .ALUsrc (ALUsrc),
   .ImmOp (ImmOp),
   .regOp2 (regOp2),
   .ALUctrl (ALUctrl),
   .ALUout (ALUout),
   .EQ (EQ)
);

endmodule

RISC-V-CPU/extend.sv
module extend #(
    parameter WIDTH = 32
) (
    //interface signals
    input   logic   [WIDTH-1:0]  Imm,                       //32 bit instruction
    input   logic                ImmSrc,                    //Control signal
    output  logic   [WIDTH-1:0]  ImmOp                      //32 bit out
);
//logic [14:0] leftover;
//assign leftover = {Imm[19:12], Imm[6:0]};

always_comb begin
    if (ImmSrc) ImmOp = { {WIDTH-12{Imm[31]}}, Imm[31:20] };                           //I-type when ImmSrc = 1
    else        ImmOp = { {WIDTH-12{Imm[31]}}, Imm[7], Imm[30:25], Imm[11:8], 1'b0 };  //B-type when ImmSrc = 0
end
endmodule

RISC-V-CPU/control.sv
module control #(
    parameter ADDRESS_WIDTH = 32
)(
    input logic EQ, //if rs1 != rs2, this is 1
    input logic [ADDRESS_WIDTH-26:0] instr, //will need more than this later , for fn3 and 7
    output logic RegWrite,
    output logic [3-1:0] ALUctrl,
    output logic ALUsrc,
    output logic ImmSrc,
    output logic PCsrc 
);

logic [6:0] opcode;
//logic [14:12] fn3;
//logic [31:25] fn7;

assign opcode = instr[6:0];
//assign fn3 = instr[14:12];
//assign fn7 = instr[31:25];

always_comb begin 
    case (opcode)
        7'b0010011: begin
            ALUctrl = 3'b000;
            ALUsrc = 1'b1;
            ImmSrc = 1'b1;
            PCsrc = 1'b0;
            RegWrite = 1'b1;
        end

        7'b1100011: begin
            ALUctrl = 3'b111; //default 0
            ALUsrc = 1'b0;
            ImmSrc = 1'b0;
            PCsrc = !EQ;
            RegWrite = 1'b0;
        end
        default: begin
            ALUctrl = 3'b0;
            ALUsrc = 1'b0;
            ImmSrc = 1'b0;
            PCsrc = 1'b1;
            RegWrite = 1'b0;
        end
    endcase
end


endmodule

RISC-V-CPU/instrmem.sv
module instrmem #(
    parameter ADDRESS_WIDTH = 32, 
              DATA_WIDTH = 32
) (
    //input logic clk,
    input logic [ADDRESS_WIDTH-1:0] A,
    output logic [DATA_WIDTH-1:0] RD
);

//The dumb method. it also works (probably. maybe?)
always_comb 
    case(A)
        32'h00000000: RD = 32'h0FF00313;
        32'h00000004: RD = 32'h00000513;
        32'h00000008: RD = 32'h00000593;
        32'h0000000c: RD = 32'h00058513;
        32'h00000010: RD = 32'h00158593;
        32'h00000014: RD = 32'hFE659CE3;
        32'h00000018: RD = 32'hFE0318E3;
        default: RD = 32'h00000000;
    endcase

/*
logic [DATA_WIDTH-1:0] rom_array [2**ADDRESS_WIDTH-1:0]; //this v big

initial begin
    $display("loading instr."); //remove
    $readmemh("instr.mem", rom_array);
end

always_ff @(posedge A, negedge A) // needs to be async, so the value changes immediately. HOW??
RD <= rom_array [A];
*/


endmodule

RISC-V-CPU/PC_Reg.sv
module PC_Reg #(
    parameter WIDTH = 32
)(
// interface signals
  input logic              clk,
  input logic              rst,
  input logic  [WIDTH-1:0] next_PC,
  output logic [WIDTH-1:0] PC

);

always_ff @ (posedge clk, posedge rst)
  if (rst) PC <= 32'b0;
  else     PC <= next_PC;

endmodule

RISC-V-CPU/PC_top.sv
module PC_top #(
  parameter WIDTH = 32


)(
  input logic    clk,
  input logic    rst,
  input logic [WIDTH-1:0] ImmOp, 
  input logic PCsrc,
  output logic [WIDTH-1:0] PC
);
  logic [WIDTH-1:0] inc_PC;
  logic [WIDTH-1:0] branch_PC;
  logic [WIDTH-1:0] next_PC;
  assign inc_PC = PC + 4; 
  assign branch_PC = PC + ImmOp; 

  assign next_PC = PCsrc ? branch_PC : inc_PC;

/*Mux_1 Mux_1 (
  .PCsrc (PCsrc),
  .inc_PC (inc_PC),
  .branch_PC (branch_PC),
  .next_PC (next_PC)
);
*/
PC_Reg PC_Reg
 (
  .clk (clk),
  .rst (rst),
  .next_PC (next_PC),
  .PC (PC)
);

endmodule

RISC-V-CPU/cpu.sv
module cpu #(
    parameter ADDRESS_WIDTH = 32
)(
    input clk,
    input rst,
    output [ADDRESS_WIDTH-1:0] a0

);
   
    // logic [ADDRESS_WIDTH-1:0] instr;
    // logic ImmSrc;
    logic EQ;
    logic [ADDRESS_WIDTH-1:0] PC;
    logic [ADDRESS_WIDTH-1:0] ImmOp;
    logic PCsrc;
    logic RegWrite;
    logic [3-1:0] ALUctrl; //needs to be 3 bit
    logic ALUsrc;
    logic ImmSrc;
    logic [ADDRESS_WIDTH-1:0] instr;
    

//blue
PC_top blue (
  .clk(clk),
  .rst(rst),
  .ImmOp(ImmOp),
  .PCsrc(PCsrc),
  .PC(PC)
);

//green
instrmem rom (
    .A(PC),
    .RD(instr)
);

control ctrl (
    .EQ(EQ),
    .instr(instr[6:0]), //how to take the last 7 bits of instr from rom
    .RegWrite(RegWrite),
    .ALUctrl(ALUctrl),
    .ALUsrc(ALUsrc),
    .ImmSrc(ImmSrc),
    .PCsrc(PCsrc)
);

extend sign_ext (
    .Imm(instr),  //same here
    .ImmSrc(ImmSrc),
    .ImmOp(ImmOp)
);

//red
red_top red(
  .ImmOp(ImmOp),
  .clk(clk),
  .RegWrite(RegWrite),
  .ALUctrl(ALUctrl),
  .ALUsrc(ALUsrc),
  .rs1(instr[19:15]), //each are 5  bits long
  .rs2(instr[24:20]), //does this work?
  .rd(instr[11:7]),

  .EQ(EQ),
  .a0(a0)
);

endmodule

RISC-V-CPU/cpu.vcd
$version Generated by VerilatedVcd $end
$date Fri Dec  2 12:16:56 2022 $end
$timescale 1ps $end

 $scope module TOP $end
  $var wire 32 S a0 [31:0] $end
  $var wire  1 Q clk $end
  $var wire  1 R rst $end
  $scope module cpu $end
   $var wire 32 Y ADDRESS_WIDTH [31:0] $end
   $var wire  3 H ALUctrl [2:0] $end
   $var wire  1 G ALUsrc $end
   $var wire  1 D EQ $end
   $var wire 32 E ImmOp [31:0] $end
   $var wire  1 G ImmSrc $end
   $var wire 32 T PC [31:0] $end
   $var wire  1 F PCsrc $end
   $var wire  1 G RegWrite $end
   $var wire 32 S a0 [31:0] $end
   $var wire  1 Q clk $end
   $var wire 32 I instr [31:0] $end
   $var wire  1 R rst $end
   $scope module blue $end
    $var wire 32 E ImmOp [31:0] $end
    $var wire 32 T PC [31:0] $end
    $var wire  1 F PCsrc $end
    $var wire 32 Y WIDTH [31:0] $end
    $var wire 32 V branch_PC [31:0] $end
    $var wire  1 Q clk $end
    $var wire 32 U inc_PC [31:0] $end
    $var wire 32 W next_PC [31:0] $end
    $var wire  1 R rst $end
    $scope module PC_Reg $end
     $var wire 32 T PC [31:0] $end
     $var wire 32 Y WIDTH [31:0] $end
     $var wire  1 Q clk $end
     $var wire 32 W next_PC [31:0] $end
     $var wire  1 R rst $end
    $upscope $end
   $upscope $end
   $scope module ctrl $end
    $var wire 32 Y ADDRESS_WIDTH [31:0] $end
    $var wire  3 H ALUctrl [2:0] $end
    $var wire  1 G ALUsrc $end
    $var wire  1 D EQ $end
    $var wire  1 G ImmSrc $end
    $var wire  1 F PCsrc $end
    $var wire  1 G RegWrite $end
    $var wire  7 J instr [6:0] $end
    $var wire  7 J opcode [6:0] $end
   $upscope $end
   $scope module red $end
    $var wire 32 Z ADDRESS_WIDTH [31:0] $end
    $var wire  3 H ALUctrl [2:0] $end
    $var wire 32 [ ALUctrl_WIDTH [31:0] $end
    $var wire 32 N ALUop1 [31:0] $end
    $var wire 32 O ALUout [31:0] $end
    $var wire  1 G ALUsrc $end
    $var wire 32 Y DATA_WIDTH [31:0] $end
    $var wire  1 D EQ $end
    $var wire 32 E ImmOp [31:0] $end
    $var wire  1 G RegWrite $end
    $var wire 32 S a0 [31:0] $end
    $var wire  1 Q clk $end
    $var wire  5 M rd [4:0] $end
    $var wire 32 X regOp2 [31:0] $end
    $var wire  5 K rs1 [4:0] $end
    $var wire  5 L rs2 [4:0] $end
    $scope module ALU $end
     $var wire  3 H ALUctrl [2:0] $end
     $var wire 32 N ALUop1 [31:0] $end
     $var wire 32 P ALUop2 [31:0] $end
     $var wire 32 O ALUout [31:0] $end
     $var wire  1 G ALUsrc $end
     $var wire 32 Y DATA_WIDTH [31:0] $end
     $var wire  1 D EQ $end
     $var wire 32 E ImmOp [31:0] $end
     $var wire 32 X regOp2 [31:0] $end
    $upscope $end
    $scope module ram $end
     $var wire  5 K AD1 [4:0] $end
     $var wire  5 L AD2 [4:0] $end
     $var wire  5 M AD3 [4:0] $end
     $var wire 32 Z ADDRESS_WIDTH [31:0] $end
     $var wire 32 Y DATA_WIDTH [31:0] $end
     $var wire 32 N RD1 [31:0] $end
     $var wire 32 X RD2 [31:0] $end
     $var wire 32 O WD3 [31:0] $end
     $var wire  1 G WE3 $end
     $var wire 32 S a0 [31:0] $end
     $var wire  1 Q clk $end
     $var wire 32 $ ram_array[0] [31:0] $end
     $var wire 32 . ram_array[10] [31:0] $end
     $var wire 32 / ram_array[11] [31:0] $end
     $var wire 32 0 ram_array[12] [31:0] $end
     $var wire 32 1 ram_array[13] [31:0] $end
     $var wire 32 2 ram_array[14] [31:0] $end
     $var wire 32 3 ram_array[15] [31:0] $end
     $var wire 32 4 ram_array[16] [31:0] $end
     $var wire 32 5 ram_array[17] [31:0] $end
     $var wire 32 6 ram_array[18] [31:0] $end
     $var wire 32 7 ram_array[19] [31:0] $end
     $var wire 32 % ram_array[1] [31:0] $end
     $var wire 32 8 ram_array[20] [31:0] $end
     $var wire 32 9 ram_array[21] [31:0] $end
     $var wire 32 : ram_array[22] [31:0] $end
     $var wire 32 ; ram_array[23] [31:0] $end
     $var wire 32 < ram_array[24] [31:0] $end
     $var wire 32 = ram_array[25] [31:0] $end
     $var wire 32 > ram_array[26] [31:0] $end
     $var wire 32 ? ram_array[27] [31:0] $end
     $var wire 32 @ ram_array[28] [31:0] $end
     $var wire 32 A ram_array[29] [31:0] $end
     $var wire 32 & ram_array[2] [31:0] $end
     $var wire 32 B ram_array[30] [31:0] $end
     $var wire 32 C ram_array[31] [31:0] $end
     $var wire 32 ' ram_array[3] [31:0] $end
     $var wire 32 ( ram_array[4] [31:0] $end
     $var wire 32 ) ram_array[5] [31:0] $end
     $var wire 32 * ram_array[6] [31:0] $end
     $var wire 32 + ram_array[7] [31:0] $end
     $var wire 32 , ram_array[8] [31:0] $end
     $var wire 32 - ram_array[9] [31:0] $end
     $scope module unnamedblk1 $end
      $var wire 32 # i [31:0] $end
     $upscope $end
    $upscope $end
   $upscope $end
   $scope module rom $end
    $var wire 32 T A [31:0] $end
    $var wire 32 Y ADDRESS_WIDTH [31:0] $end
    $var wire 32 Y DATA_WIDTH [31:0] $end
    $var wire 32 I RD [31:0] $end
   $upscope $end
   $scope module sign_ext $end
    $var wire 32 I Imm [31:0] $end
    $var wire 32 E ImmOp [31:0] $end
    $var wire  1 G ImmSrc $end
    $var wire 32 Y WIDTH [31:0] $end
   $upscope $end
  $upscope $end
 $upscope $end
$enddefinitions $end


#0
b00000000000000000000000000000000 #
b00000000000000000000000000000000 $
b00000000000000000000000000000000 %
b00000000000000000000000000000000 &
b00000000000000000000000000000000 '
b00000000000000000000000000000000 (
b00000000000000000000000000000000 )
b00000000000000000000000000000000 *
b00000000000000000000000000000000 +
b00000000000000000000000000000000 ,
b00000000000000000000000000000000 -
b00000000000000000000000000000000 .
b00000000000000000000000000000000 /
b00000000000000000000000000000000 0
b00000000000000000000000000000000 1
b00000000000000000000000000000000 2
b00000000000000000000000000000000 3
b00000000000000000000000000000000 4
b00000000000000000000000000000000 5
b00000000000000000000000000000000 6
b00000000000000000000000000000000 7
b00000000000000000000000000000000 8
b00000000000000000000000000000000 9
b00000000000000000000000000000000 :
b00000000000000000000000000000000 ;
b00000000000000000000000000000000 <
b00000000000000000000000000000000 =
b00000000000000000000000000000000 >
b00000000000000000000000000000000 ?
b00000000000000000000000000000000 @
b00000000000000000000000000000000 A
b00000000000000000000000000000000 B
b00000000000000000000000000000000 C
1D
b00000000000000000000000000000000 E
1F
0G
b000 H
b00000000000000000000000000000000 I
b0000000 J
b00000 K
b00000 L
b00000 M
b00000000000000000000000000000000 N
b00000000000000000000000000000000 O
b00000000000000000000000000000000 P
1Q
0R
b00000000000000000000000000000000 S
b00000000000000000000000000000000 T
b00000000000000000000000000000100 U
b00000000000000000000000000000000 V
b00000000000000000000000000000000 W
b00000000000000000000000000000000 X
b00000000000000000000000000100000 Y
b00000000000000000000000000000101 Z
b00000000000000000000000000000011 [
#1
b00000000000000000000000000100000 #
0D
b00000000000000000000000011111111 E
0F
1G
b00001111111100000000001100010011 I
b0010011 J
b11111 L
b00110 M
b00000000000000000000000011111111 O
b00000000000000000000000011111111 P
0Q
b00000000000000000000000011111111 V
b00000000000000000000000000000100 W
#2
b00000000000000000000000011111111 *
1D
b00000000000000000000000000000000 E
b00000000000000000000010100010011 I
b00000 L
b01010 M
b00000000000000000000000000000000 O
b00000000000000000000000000000000 P
1Q
b00000000000000000000000000000100 T
b00000000000000000000000000001000 U
b00000000000000000000000000000100 V
b00000000000000000000000000001000 W
#3
0Q
#4
b00000000000000000000010110010011 I
b01011 M
1Q
b00000000000000000000000000001000 T
b00000000000000000000000000001100 U
b00000000000000000000000000001000 V
b00000000000000000000000000001100 W
#5
0Q
#6
b00000000000001011000010100010011 I
b01011 K
b01010 M
1Q
b00000000000000000000000000001100 T
b00000000000000000000000000010000 U
b00000000000000000000000000001100 V
b00000000000000000000000000010000 W
#7
0Q
#8
0D
b00000000000000000000000000000001 E
b00000000000101011000010110010011 I
b00001 L
b01011 M
b00000000000000000000000000000001 O
b00000000000000000000000000000001 P
1Q
b00000000000000000000000000010000 T
b00000000000000000000000000010100 U
b00000000000000000000000000010001 V
b00000000000000000000000000010100 W
#9
0Q
#10
b00000000000000000000000000000001 /
b11111111111111111111111111111000 E
1F
0G
b111 H
b11111110011001011001110011100011 I
b1100011 J
b00110 L
b11001 M
b00000000000000000000000000000001 N
b00000000000000000000000000000000 O
b00000000000000000000000011111111 P
1Q
b00000000000000000000000000010100 T
b00000000000000000000000000011000 U
b00000000000000000000000000001100 V
b00000000000000000000000000001100 W
b00000000000000000000000011111111 X
#11
0Q
#12
b00000000000000000000000000000000 E
0F
1G
b000 H
b00000000000001011000010100010011 I
b0010011 J
b00000 L
b01010 M
b00000000000000000000000000000001 O
b00000000000000000000000000000000 P
1Q
b00000000000000000000000000001100 T
b00000000000000000000000000010000 U
b00000000000000000000000000010000 W
b00000000000000000000000000000000 X
#13
0Q
#14
b00000000000000000000000000000001 .
1D
b00000000000000000000000000000001 E
b00000000000101011000010110010011 I
b00001 L
b01011 M
b00000000000000000000000000000010 O
b00000000000000000000000000000001 P
1Q
b00000000000000000000000000000001 S
b00000000000000000000000000010000 T
b00000000000000000000000000010100 U
b00000000000000000000000000010001 V
b00000000000000000000000000010100 W
#15
0Q
#16
b00000000000000000000000000000010 /
0D
b11111111111111111111111111111000 E
1F
0G
b111 H
b11111110011001011001110011100011 I
b1100011 J
b00110 L
b11001 M
b00000000000000000000000000000010 N
b00000000000000000000000000000000 O
b00000000000000000000000011111111 P
1Q
b00000000000000000000000000010100 T
b00000000000000000000000000011000 U
b00000000000000000000000000001100 V
b00000000000000000000000000001100 W
b00000000000000000000000011111111 X
#17
0Q
#18
b00000000000000000000000000000000 E
0F
1G
b000 H
b00000000000001011000010100010011 I
b0010011 J
b00000 L
b01010 M
b00000000000000000000000000000010 O
b00000000000000000000000000000000 P
1Q
b00000000000000000000000000001100 T
b00000000000000000000000000010000 U
b00000000000000000000000000010000 W
b00000000000000000000000000000000 X
#19
0Q
#20
b00000000000000000000000000000010 .
b00000000000000000000000000000001 E
b00000000000101011000010110010011 I
b00001 L
b01011 M
b00000000000000000000000000000011 O
b00000000000000000000000000000001 P
1Q
b00000000000000000000000000000010 S
b00000000000000000000000000010000 T
b00000000000000000000000000010100 U
b00000000000000000000000000010001 V
b00000000000000000000000000010100 W
#21
0Q
#22
b00000000000000000000000000000011 /
b11111111111111111111111111111000 E
1F
0G
b111 H
b11111110011001011001110011100011 I
b1100011 J
b00110 L
b11001 M
b00000000000000000000000000000011 N
b00000000000000000000000000000000 O
b00000000000000000000000011111111 P
1Q
b00000000000000000000000000010100 T
b00000000000000000000000000011000 U
b00000000000000000000000000001100 V
b00000000000000000000000000001100 W
b00000000000000000000000011111111 X
#23
0Q
#24
b00000000000000000000000000000000 E
0F
1G
b000 H
b00000000000001011000010100010011 I
b0010011 J
b00000 L
b01010 M
b00000000000000000000000000000011 O
b00000000000000000000000000000000 P
1Q
b00000000000000000000000000001100 T
b00000000000000000000000000010000 U
b00000000000000000000000000010000 W
b00000000000000000000000000000000 X
#25
0Q
#26
b00000000000000000000000000000011 .
b00000000000000000000000000000001 E
b00000000000101011000010110010011 I
b00001 L
b01011 M
b00000000000000000000000000000100 O
b00000000000000000000000000000001 P
1Q
b00000000000000000000000000000011 S
b00000000000000000000000000010000 T
b00000000000000000000000000010100 U
b00000000000000000000000000010001 V
b00000000000000000000000000010100 W
#27
0Q
#28
b00000000000000000000000000000100 /
b11111111111111111111111111111000 E
1F
0G
b111 H
b11111110011001011001110011100011 I
b1100011 J
b00110 L
b11001 M
b00000000000000000000000000000100 N
b00000000000000000000000000000000 O
b00000000000000000000000011111111 P
1Q
b00000000000000000000000000010100 T
b00000000000000000000000000011000 U
b00000000000000000000000000001100 V
b00000000000000000000000000001100 W
b00000000000000000000000011111111 X
#29
0Q
#30
b00000000000000000000000000000000 E
0F
1G
b000 H
b00000000000001011000010100010011 I
b0010011 J
b00000 L
b01010 M
b00000000000000000000000000000100 O
b00000000000000000000000000000000 P
1Q
b00000000000000000000000000001100 T
b00000000000000000000000000010000 U
b00000000000000000000000000010000 W
b00000000000000000000000000000000 X
#31
0Q
#32
b00000000000000000000000000000100 .
b00000000000000000000000000000001 E
b00000000000101011000010110010011 I
b00001 L
b01011 M
b00000000000000000000000000000101 O
b00000000000000000000000000000001 P
1Q
b00000000000000000000000000000100 S
b00000000000000000000000000010000 T
b00000000000000000000000000010100 U
b00000000000000000000000000010001 V
b00000000000000000000000000010100 W
#33
0Q
#34
b00000000000000000000000000000101 /
b11111111111111111111111111111000 E
1F
0G
b111 H
b11111110011001011001110011100011 I
b1100011 J
b00110 L
b11001 M
b00000000000000000000000000000101 N
b00000000000000000000000000000000 O
b00000000000000000000000011111111 P
1Q
b00000000000000000000000000010100 T
b00000000000000000000000000011000 U
b00000000000000000000000000001100 V
b00000000000000000000000000001100 W
b00000000000000000000000011111111 X
#35
0Q
#36
b00000000000000000000000000000000 E
0F
1G
b000 H
b00000000000001011000010100010011 I
b0010011 J
b00000 L
b01010 M
b00000000000000000000000000000101 O
b00000000000000000000000000000000 P
1Q
b00000000000000000000000000001100 T
b00000000000000000000000000010000 U
b00000000000000000000000000010000 W
b00000000000000000000000000000000 X
#37
0Q
#38
b00000000000000000000000000000101 .
b00000000000000000000000000000001 E
b00000000000101011000010110010011 I
b00001 L
b01011 M
b00000000000000000000000000000110 O
b00000000000000000000000000000001 P
1Q
b00000000000000000000000000000101 S
b00000000000000000000000000010000 T
b00000000000000000000000000010100 U
b00000000000000000000000000010001 V
b00000000000000000000000000010100 W
#39
0Q
#40
b00000000000000000000000000000110 /
b11111111111111111111111111111000 E
1F
0G
b111 H
b11111110011001011001110011100011 I
b1100011 J
b00110 L
b11001 M
b00000000000000000000000000000110 N
b00000000000000000000000000000000 O
b00000000000000000000000011111111 P
1Q
b00000000000000000000000000010100 T
b00000000000000000000000000011000 U
b00000000000000000000000000001100 V
b00000000000000000000000000001100 W
b00000000000000000000000011111111 X
#41
0Q
#42
b00000000000000000000000000000000 E
0F
1G
b000 H
b00000000000001011000010100010011 I
b0010011 J
b00000 L
b01010 M
b00000000000000000000000000000110 O
b00000000000000000000000000000000 P
1Q
b00000000000000000000000000001100 T
b00000000000000000000000000010000 U
b00000000000000000000000000010000 W
b00000000000000000000000000000000 X
#43
0Q
#44
b00000000000000000000000000000110 .
b00000000000000000000000000000001 E
b00000000000101011000010110010011 I
b00001 L
b01011 M
b00000000000000000000000000000111 O
b00000000000000000000000000000001 P
1Q
b00000000000000000000000000000110 S
b00000000000000000000000000010000 T
b00000000000000000000000000010100 U
b00000000000000000000000000010001 V
b00000000000000000000000000010100 W
#45
0Q
#46
b00000000000000000000000000000111 /
b11111111111111111111111111111000 E
1F
0G
b111 H
b11111110011001011001110011100011 I
b1100011 J
b00110 L
b11001 M
b00000000000000000000000000000111 N
b00000000000000000000000000000000 O
b00000000000000000000000011111111 P
1Q
b00000000000000000000000000010100 T
b00000000000000000000000000011000 U
b00000000000000000000000000001100 V
b00000000000000000000000000001100 W
b00000000000000000000000011111111 X
#47
0Q
#48
b00000000000000000000000000000000 E
0F
1G
b000 H
b00000000000001011000010100010011 I
b0010011 J
b00000 L
b01010 M
b00000000000000000000000000000111 O
b00000000000000000000000000000000 P
1Q
b00000000000000000000000000001100 T
b00000000000000000000000000010000 U
b00000000000000000000000000010000 W
b00000000000000000000000000000000 X
#49
0Q
#50
b00000000000000000000000000000111 .
b00000000000000000000000000000001 E
b00000000000101011000010110010011 I
b00001 L
b01011 M
b00000000000000000000000000001000 O
b00000000000000000000000000000001 P
1Q
b00000000000000000000000000000111 S
b00000000000000000000000000010000 T
b00000000000000000000000000010100 U
b00000000000000000000000000010001 V
b00000000000000000000000000010100 W
#51
0Q
#52
b00000000000000000000000000001000 /
b11111111111111111111111111111000 E
1F
0G
b111 H
b11111110011001011001110011100011 I
b1100011 J
b00110 L
b11001 M
b00000000000000000000000000001000 N
b00000000000000000000000000000000 O
b00000000000000000000000011111111 P
1Q
b00000000000000000000000000010100 T
b00000000000000000000000000011000 U
b00000000000000000000000000001100 V
b00000000000000000000000000001100 W
b00000000000000000000000011111111 X
#53
0Q
#54
b00000000000000000000000000000000 E
0F
1G
b000 H
b00000000000001011000010100010011 I
b0010011 J
b00000 L
b01010 M
b00000000000000000000000000001000 O
b00000000000000000000000000000000 P
1Q
b00000000000000000000000000001100 T
b00000000000000000000000000010000 U
b00000000000000000000000000010000 W
b00000000000000000000000000000000 X
#55
0Q
#56
b00000000000000000000000000001000 .
b00000000000000000000000000000001 E
b00000000000101011000010110010011 I
b00001 L
b01011 M
b00000000000000000000000000001001 O
b00000000000000000000000000000001 P
1Q
b00000000000000000000000000001000 S
b00000000000000000000000000010000 T
b00000000000000000000000000010100 U
b00000000000000000000000000010001 V
b00000000000000000000000000010100 W
#57
0Q
#58
b00000000000000000000000000001001 /
b11111111111111111111111111111000 E
1F
0G
b111 H
b11111110011001011001110011100011 I
b1100011 J
b00110 L
b11001 M
b00000000000000000000000000001001 N
b00000000000000000000000000000000 O
b00000000000000000000000011111111 P
1Q
b00000000000000000000000000010100 T
b00000000000000000000000000011000 U
b00000000000000000000000000001100 V
b00000000000000000000000000001100 W
b00000000000000000000000011111111 X
#59
0Q
#60
b00000000000000000000000000000000 E
0F
1G
b000 H
b00000000000001011000010100010011 I
b0010011 J
b00000 L
b01010 M
b00000000000000000000000000001001 O
b00000000000000000000000000000000 P
1Q
b00000000000000000000000000001100 T
b00000000000000000000000000010000 U
b00000000000000000000000000010000 W
b00000000000000000000000000000000 X
#61
0Q
#62
b00000000000000000000000000001001 .
b00000000000000000000000000000001 E
b00000000000101011000010110010011 I
b00001 L
b01011 M
b00000000000000000000000000001010 O
b00000000000000000000000000000001 P
1Q
b00000000000000000000000000001001 S
b00000000000000000000000000010000 T
b00000000000000000000000000010100 U
b00000000000000000000000000010001 V
b00000000000000000000000000010100 W
#63
0Q
#64
b00000000000000000000000000001010 /
b11111111111111111111111111111000 E
1F
0G
b111 H
b11111110011001011001110011100011 I
b1100011 J
b00110 L
b11001 M
b00000000000000000000000000001010 N
b00000000000000000000000000000000 O
b00000000000000000000000011111111 P
1Q
b00000000000000000000000000010100 T
b00000000000000000000000000011000 U
b00000000000000000000000000001100 V
b00000000000000000000000000001100 W
b00000000000000000000000011111111 X
#65
0Q
#66
b00000000000000000000000000000000 E
0F
1G
b000 H
b00000000000001011000010100010011 I
b0010011 J
b00000 L
b01010 M
b00000000000000000000000000001010 O
b00000000000000000000000000000000 P
1Q
b00000000000000000000000000001100 T
b00000000000000000000000000010000 U
b00000000000000000000000000010000 W
b00000000000000000000000000000000 X
#67
0Q
#68
b00000000000000000000000000001010 .
b00000000000000000000000000000001 E
b00000000000101011000010110010011 I
b00001 L
b01011 M
b00000000000000000000000000001011 O
b00000000000000000000000000000001 P
1Q
b00000000000000000000000000001010 S
b00000000000000000000000000010000 T
b00000000000000000000000000010100 U
b00000000000000000000000000010001 V
b00000000000000000000000000010100 W
#69
0Q
#70
b00000000000000000000000000001011 /
b11111111111111111111111111111000 E
1F
0G
b111 H
b11111110011001011001110011100011 I
b1100011 J
b00110 L
b11001 M
b00000000000000000000000000001011 N
b00000000000000000000000000000000 O
b00000000000000000000000011111111 P
1Q
b00000000000000000000000000010100 T
b00000000000000000000000000011000 U
b00000000000000000000000000001100 V
b00000000000000000000000000001100 W
b00000000000000000000000011111111 X
#71
0Q
#72
b00000000000000000000000000000000 E
0F
1G
b000 H
b00000000000001011000010100010011 I
b0010011 J
b00000 L
b01010 M
b00000000000000000000000000001011 O
b00000000000000000000000000000000 P
1Q
b00000000000000000000000000001100 T
b00000000000000000000000000010000 U
b00000000000000000000000000010000 W
b00000000000000000000000000000000 X
#73
0Q
#74
b00000000000000000000000000001011 .
b00000000000000000000000000000001 E
b00000000000101011000010110010011 I
b00001 L
b01011 M
b00000000000000000000000000001100 O
b00000000000000000000000000000001 P
1Q
b00000000000000000000000000001011 S
b00000000000000000000000000010000 T
b00000000000000000000000000010100 U
b00000000000000000000000000010001 V
b00000000000000000000000000010100 W
#75
0Q
#76
b00000000000000000000000000001100 /
b11111111111111111111111111111000 E
1F
0G
b111 H
b11111110011001011001110011100011 I
b1100011 J
b00110 L
b11001 M
b00000000000000000000000000001100 N
b00000000000000000000000000000000 O
b00000000000000000000000011111111 P
1Q
b00000000000000000000000000010100 T
b00000000000000000000000000011000 U
b00000000000000000000000000001100 V
b00000000000000000000000000001100 W
b00000000000000000000000011111111 X
#77
0Q
#78
b00000000000000000000000000000000 E
0F
1G
b000 H
b00000000000001011000010100010011 I
b0010011 J
b00000 L
b01010 M
b00000000000000000000000000001100 O
b00000000000000000000000000000000 P
1Q
b00000000000000000000000000001100 T
b00000000000000000000000000010000 U
b00000000000000000000000000010000 W
b00000000000000000000000000000000 X
#79
0Q
