RISC-V CPU/extend.sv
module extend #(
    parameter WIDTH = 32
) (
    //interface signals
    input   logic   [WIDTH-1:0]  Imm,                       //32 bit instruction
    input   logic                ImmSrc,                    //Control signal
    output  logic   [WIDTH-1:0]  ImmOp                      //32 bit out
);

always_comb begin
    if (ImmSrc) ImmOp = { {WIDTH-12{Imm[31]}}, Imm[31:20] };                           //I-type when ImmSrc = 1
    else        ImmOp = { {WIDTH-12{Imm[31]}}, Imm[7], Imm[30:25], Imm[11:8], 1'b0 };  //B-type when ImmSrc = 0
end
endmodule

RISC-V CPU/control.sv
module control #(
    parameter ADDRESS_WIDTH = 32
)(
    input logic EQ, //if rs1 != rs2, this is 1
    input logic [ADDRESS_WIDTH-1:0] instr, //will need more than this later , for fn3 and 7
    output logic RegWrite,
    output logic ALUctrl,
    output logic ALUsrc,
    output logic ImmSrc,
    output logic PCsrc 
);

logic [4:0] flags;
logic [6:0] opcode;
logic [14:12] fn3;
logic [31:25] fn7;

assign flags = {RegWrite, ALUctrl, ALUsrc, ImmSrc, PCsrc};
assign opcode = instr[6:0];
assign fn3 = instr[14:12];
assign fn7 = instr[31:25];

always_comb
    casez(opcode)
        7'b0010011: flags = 5'b10110; //for op = 19
        7'b1100011: flags = EQ ? 5'b01001: 5'b00000; //for op = 99 and EQ is 1
        default: flags = 5'b00000;
    endcase

assign {RegWrite, ALUctrl, ALUsrc, ImmSrc, PCsrc} = flags;
/*
logic branch = 7b'1100011; //99
logic imm = 2b'11;  //19

    //if certain bits are output from the instr mem, then certain flags turn on
    //THink of a better way to do this

    assign RegWrite = (instr == imm) ? 1'b1 : 1'b0; 
    assign ALUctrl = (instr == branch && EQ) ? 1'b1 : 1'b0;   
    assign ALUsrc = (instr == imm) ? 1'b1 : 1'b0;    
    assign ImmSrc = (instr == imm) ? 1'b1 : 1'b0;    
    assign PCsrc = (instr == branch && EQ) ? 1'b1 : 1'b0;
*/

endmodule

Green/instrmem.sv
module instrmem #(
    parameter ADDRESS_WIDTH = 32, 
              DATA_WIDTH = 32
) (
    //input logic clk,
    input logic [ADDRESS_WIDTH-1:0] A,
    output logic [DATA_WIDTH-1:0] RD
);

//The dumb method. it also works (probably. maybe?)
always_comb 
    case(A)
        32h'00000000: RD = 32h'0FF00313;
        32h'00000004: RD = 32h'00000513;
        32h'00000008: RD = 32h'00000593;
        32h'0000000c: RD = 32h'00058513;
        32h'00000010: RD = 32h'00158593;
        32h'00000014: RD = 32h'FE659CE3;
        32h'00000018: RD = 32h'FE0318E3;
        default: RD = 32h'00000000;
    endcase

/*
logic [DATA_WIDTH-1:0] rom_array [2**ADDRESS_WIDTH-1:0]; //this v big

initial begin
    $display("loading instr."); //remove
    $readmemh("instr.mem", rom_array);
end

always_ff @(posedge A, negedge A) // needs to be async, so the value changes immediately. HOW??
RD <= rom_array [A];
*/


endmodule

RISC-V-CPU/PC_Reg.sv
module PC_Reg #(
    parameter WIDTH = 32
)(
// interface signals
  input logic              clk,
  input logic              rst,
  input logic  [WIDTH-1:0] next_PC,
  output logic [WIDTH-1:0] PC

);

always_ff @ (posedge clk, posedge rst)
  if (rst) PC <= 32'b0;
  else     PC <= next_PC;

endmodule

RISC-V-CPU/PC_top.sv
module PC_top #(
  parameter WIDTH = 32


)(
  input logic    clk,
  input logic    rst,
  input logic [WIDTH-1:0] ImmOp, 
  input logic PCsrc,
  output logic [WIDTH-1:0] PC
);
  logic [WIDTH-1:0] inc_PC;
  logic [WIDTH-1:0] branch_PC;
  logic [WIDTH-1:0] next_PC;
  assign inc_PC = PC + 4; 
  assign branch_PC = PC + ImmOp; 

  assign next_PC = PCsrc ? branch_PC : inc_PC;

/*Mux_1 Mux_1 (
  .PCsrc (PCsrc),
  .inc_PC (inc_PC),
  .branch_PC (branch_PC),
  .next_PC (next_PC)
);
*/
PC_Reg PC_Reg
 (
  .clk (clk),
  .rst (rst),
  .next_PC (next_PC),
  .PC (PC)
);

endmodule

RISC-V CPU/cpu.sv
module cpu #(
    parameter ADDRESS_WIDTH = 32
)(
    input clk,
    input rst,

    input logic EQ,

    output logic RegWrite,
    output logic ALUctrl,
    output logic ALUsrc,
    output logic PCsrc,

    output logic [ADDRESS_WIDTH-1:0] instr,
    output logic ImmSrc,
    output logic [ADDRESS_WIDTH-1:0] PC
);
   
    // logic [ADDRESS_WIDTH-1:0] instr;
    // logic ImmSrc;
    // logic [ADDRESS_WIDTH-1:0] PC;
    logic [ADDRESS_WIDTH-1:0] ImmOp;

//blue
PC_top blue (
  .clk(clk),
  .rst(rst),
  .ImmOp(ImmOp),
  .PCsrc(PCsrc),
  .PC(PC)
);

//green
// counter addrCount (
//     .clk (clk),
//     .rst (rst),
//     .en (en),
//     .count (PC)
// );


instrmem rom (
    .A(PC),
    .RD(instr)
);

control ctrl (
    .EQ(EQ),
    .instr(instr), //how to take the last 7 bits of instr from rom
    .RegWrite(RegWrite),
    .ALUctrl(ALUctrl),
    .ALUsrc(ALUsrc),
    .ImmSrc(ImmSrc),
    .PCsrc(PCsrc)
);

extend sign_ext (
    .Imm(instr),  //same here
    .ImmSrc(ImmSrc),
    .ImmOp(ImmOp)
);

endmodule

RISC-V CPU/cpu.vcd
$version Generated by VerilatedVcd $end
$date Fri Nov 25 11:40:19 2022 $end
$timescale 1ps $end

 $scope module TOP $end
  $var wire  1 ' ALUctrl $end
  $var wire  1 ( ALUsrc $end
  $var wire  1 % EQ $end
  $var wire  1 + ImmSrc $end
  $var wire 32 , PC [31:0] $end
  $var wire  1 ) PCsrc $end
  $var wire  1 & RegWrite $end
  $var wire  1 # clk $end
  $var wire 32 * instr [31:0] $end
  $var wire  1 $ rst $end
  $scope module cpu $end
   $var wire 32 5 ADDRESS_WIDTH [31:0] $end
   $var wire  1 ' ALUctrl $end
   $var wire  1 ( ALUsrc $end
   $var wire  1 % EQ $end
   $var wire 32 - ImmOp [31:0] $end
   $var wire  1 + ImmSrc $end
   $var wire 32 , PC [31:0] $end
   $var wire  1 ) PCsrc $end
   $var wire  1 & RegWrite $end
   $var wire  1 # clk $end
   $var wire 32 * instr [31:0] $end
   $var wire  1 $ rst $end
   $scope module blue $end
    $var wire 32 - ImmOp [31:0] $end
    $var wire 32 , PC [31:0] $end
    $var wire  1 ) PCsrc $end
    $var wire 32 5 WIDTH [31:0] $end
    $var wire 32 / branch_PC [31:0] $end
    $var wire  1 # clk $end
    $var wire 32 . inc_PC [31:0] $end
    $var wire 32 0 next_PC [31:0] $end
    $var wire  1 $ rst $end
    $scope module PC_Reg $end
     $var wire 32 , PC [31:0] $end
     $var wire 32 5 WIDTH [31:0] $end
     $var wire  1 # clk $end
     $var wire 32 0 next_PC [31:0] $end
     $var wire  1 $ rst $end
    $upscope $end
   $upscope $end
   $scope module ctrl $end
    $var wire 32 5 ADDRESS_WIDTH [31:0] $end
    $var wire  1 ' ALUctrl $end
    $var wire  1 ( ALUsrc $end
    $var wire  1 % EQ $end
    $var wire  1 + ImmSrc $end
    $var wire  1 ) PCsrc $end
    $var wire  1 & RegWrite $end
    $var wire  5 1 flags [4:0] $end
    $var wire  3 3 fn3 [14:12] $end
    $var wire  7 4 fn7 [31:25] $end
    $var wire 32 * instr [31:0] $end
    $var wire  7 2 opcode [6:0] $end
   $upscope $end
   $scope module rom $end
    $var wire 32 , A [31:0] $end
    $var wire 32 5 ADDRESS_WIDTH [31:0] $end
    $var wire 32 5 DATA_WIDTH [31:0] $end
    $var wire 32 * RD [31:0] $end
   $upscope $end
   $scope module sign_ext $end
    $var wire 32 * Imm [31:0] $end
    $var wire 32 - ImmOp [31:0] $end
    $var wire  1 + ImmSrc $end
    $var wire 32 5 WIDTH [31:0] $end
   $upscope $end
  $upscope $end
 $upscope $end
$enddefinitions $end


#0
1#
1$
0%
0&
0'
0(
0)
b00000000000000000000000000000000 *
0+
b00000000000000000000000000000000 ,
b00000000000000000000000000000000 -
b00000000000000000000000000000100 .
b00000000000000000000000000000000 /
b00000000000000000000000000000100 0
b00000 1
b0000000 2
b000 3
b0000000 4
b00000000000000000000000000100000 5
#1
0#
1&
1(
b00001111111100000000001100010011 *
1+
b00000000000000000000000011111111 -
b00000000000000000000000011111111 /
b10110 1
b0010011 2
b0000111 4
#2
1#
0$
1%
#3
0#
#4
1#
b00000000000000000000010100010011 *
b00000000000000000000000000000100 ,
b00000000000000000000000000000000 -
b00000000000000000000000000001000 .
b00000000000000000000000000000100 /
b00000000000000000000000000001000 0
b0000000 4
#5
0#
#6
1#
b00000000000000000000010110010011 *
b00000000000000000000000000001000 ,
b00000000000000000000000000001100 .
b00000000000000000000000000001000 /
b00000000000000000000000000001100 0
#7
0#
#8
1#
b00000000000001011000010100010011 *
b00000000000000000000000000001100 ,
b00000000000000000000000000010000 .
b00000000000000000000000000001100 /
b00000000000000000000000000010000 0
#9
0#
#10
1#
b00000000000101011000010110010011 *
b00000000000000000000000000010000 ,
b00000000000000000000000000000001 -
b00000000000000000000000000010100 .
b00000000000000000000000000010001 /
b00000000000000000000000000010100 0
#11
0#
#12
1#
0&
1'
0(
1)
b11111110011001011001110011100011 *
0+
b00000000000000000000000000010100 ,
b11111111111111111111111111111000 -
b00000000000000000000000000011000 .
b00000000000000000000000000001100 /
b00000000000000000000000000001100 0
b01001 1
b1100011 2
b001 3
b1111111 4
#13
0#
#14
1#
1&
0'
1(
0)
b00000000000001011000010100010011 *
1+
b00000000000000000000000000001100 ,
b00000000000000000000000000000000 -
b00000000000000000000000000010000 .
b00000000000000000000000000010000 0
b10110 1
b0010011 2
b000 3
b0000000 4
#15
0#
#16
1#
b00000000000101011000010110010011 *
b00000000000000000000000000010000 ,
b00000000000000000000000000000001 -
b00000000000000000000000000010100 .
b00000000000000000000000000010001 /
b00000000000000000000000000010100 0
#17
0#
#18
1#
0&
1'
0(
1)
b11111110011001011001110011100011 *
0+
b00000000000000000000000000010100 ,
b11111111111111111111111111111000 -
b00000000000000000000000000011000 .
b00000000000000000000000000001100 /
b00000000000000000000000000001100 0
b01001 1
b1100011 2
b001 3
b1111111 4
#19
0#
#20
1#
1&
0'
1(
0)
b00000000000001011000010100010011 *
1+
b00000000000000000000000000001100 ,
b00000000000000000000000000000000 -
b00000000000000000000000000010000 .
b00000000000000000000000000010000 0
b10110 1
b0010011 2
b000 3
b0000000 4
#21
0#
#22
1#
b00000000000101011000010110010011 *
b00000000000000000000000000010000 ,
b00000000000000000000000000000001 -
b00000000000000000000000000010100 .
b00000000000000000000000000010001 /
b00000000000000000000000000010100 0
#23
0#
#24
1#
0&
1'
0(
1)
b11111110011001011001110011100011 *
0+
b00000000000000000000000000010100 ,
b11111111111111111111111111111000 -
b00000000000000000000000000011000 .
b00000000000000000000000000001100 /
b00000000000000000000000000001100 0
b01001 1
b1100011 2
b001 3
b1111111 4
#25
0#
#26
1#
1&
0'
1(
0)
b00000000000001011000010100010011 *
1+
b00000000000000000000000000001100 ,
b00000000000000000000000000000000 -
b00000000000000000000000000010000 .
b00000000000000000000000000010000 0
b10110 1
b0010011 2
b000 3
b0000000 4
#27
0#
#28
1#
b00000000000101011000010110010011 *
b00000000000000000000000000010000 ,
b00000000000000000000000000000001 -
b00000000000000000000000000010100 .
b00000000000000000000000000010001 /
b00000000000000000000000000010100 0
#29
0#
#30
1#
0&
1'
0(
1)
b11111110011001011001110011100011 *
0+
b00000000000000000000000000010100 ,
b11111111111111111111111111111000 -
b00000000000000000000000000011000 .
b00000000000000000000000000001100 /
b00000000000000000000000000001100 0
b01001 1
b1100011 2
b001 3
b1111111 4
#31
0#
#32
1#
1&
0'
1(
0)
b00000000000001011000010100010011 *
1+
b00000000000000000000000000001100 ,
b00000000000000000000000000000000 -
b00000000000000000000000000010000 .
b00000000000000000000000000010000 0
b10110 1
b0010011 2
b000 3
b0000000 4
#33
0#
#34
1#
b00000000000101011000010110010011 *
b00000000000000000000000000010000 ,
b00000000000000000000000000000001 -
b00000000000000000000000000010100 .
b00000000000000000000000000010001 /
b00000000000000000000000000010100 0
#35
0#
#36
1#
0&
1'
0(
1)
b11111110011001011001110011100011 *
0+
b00000000000000000000000000010100 ,
b11111111111111111111111111111000 -
b00000000000000000000000000011000 .
b00000000000000000000000000001100 /
b00000000000000000000000000001100 0
b01001 1
b1100011 2
b001 3
b1111111 4
#37
0#
#38
1#
1&
0'
1(
0)
b00000000000001011000010100010011 *
1+
b00000000000000000000000000001100 ,
b00000000000000000000000000000000 -
b00000000000000000000000000010000 .
b00000000000000000000000000010000 0
b10110 1
b0010011 2
b000 3
b0000000 4
#39
0#
#40
1#
b00000000000101011000010110010011 *
b00000000000000000000000000010000 ,
b00000000000000000000000000000001 -
b00000000000000000000000000010100 .
b00000000000000000000000000010001 /
b00000000000000000000000000010100 0
#41
0#
#42
1#
0&
1'
0(
1)
b11111110011001011001110011100011 *
0+
b00000000000000000000000000010100 ,
b11111111111111111111111111111000 -
b00000000000000000000000000011000 .
b00000000000000000000000000001100 /
b00000000000000000000000000001100 0
b01001 1
b1100011 2
b001 3
b1111111 4
#43
0#
#44
1#
1&
0'
1(
0)
b00000000000001011000010100010011 *
1+
b00000000000000000000000000001100 ,
b00000000000000000000000000000000 -
b00000000000000000000000000010000 .
b00000000000000000000000000010000 0
b10110 1
b0010011 2
b000 3
b0000000 4
#45
0#
#46
1#
b00000000000101011000010110010011 *
b00000000000000000000000000010000 ,
b00000000000000000000000000000001 -
b00000000000000000000000000010100 .
b00000000000000000000000000010001 /
b00000000000000000000000000010100 0
#47
0#
#48
1#
0&
1'
0(
1)
b11111110011001011001110011100011 *
0+
b00000000000000000000000000010100 ,
b11111111111111111111111111111000 -
b00000000000000000000000000011000 .
b00000000000000000000000000001100 /
b00000000000000000000000000001100 0
b01001 1
b1100011 2
b001 3
b1111111 4
#49
0#
#50
1#
1&
0'
1(
0)
b00000000000001011000010100010011 *
1+
b00000000000000000000000000001100 ,
b00000000000000000000000000000000 -
b00000000000000000000000000010000 .
b00000000000000000000000000010000 0
b10110 1
b0010011 2
b000 3
b0000000 4
#51
0#
#52
1#
b00000000000101011000010110010011 *
b00000000000000000000000000010000 ,
b00000000000000000000000000000001 -
b00000000000000000000000000010100 .
b00000000000000000000000000010001 /
b00000000000000000000000000010100 0
#53
0#
#54
1#
0&
1'
0(
1)
b11111110011001011001110011100011 *
0+
b00000000000000000000000000010100 ,
b11111111111111111111111111111000 -
b00000000000000000000000000011000 .
b00000000000000000000000000001100 /
b00000000000000000000000000001100 0
b01001 1
b1100011 2
b001 3
b1111111 4
#55
0#
#56
1#
1&
0'
1(
0)
b00000000000001011000010100010011 *
1+
b00000000000000000000000000001100 ,
b00000000000000000000000000000000 -
b00000000000000000000000000010000 .
b00000000000000000000000000010000 0
b10110 1
b0010011 2
b000 3
b0000000 4
#57
0#
#58
1#
b00000000000101011000010110010011 *
b00000000000000000000000000010000 ,
b00000000000000000000000000000001 -
b00000000000000000000000000010100 .
b00000000000000000000000000010001 /
b00000000000000000000000000010100 0
#59
0#
#60
1#
0&
1'
0(
1)
b11111110011001011001110011100011 *
0+
b00000000000000000000000000010100 ,
b11111111111111111111111111111000 -
b00000000000000000000000000011000 .
b00000000000000000000000000001100 /
b00000000000000000000000000001100 0
b01001 1
b1100011 2
b001 3
b1111111 4
#61
0#
#62
1#
1&
0'
1(
0)
b00000000000001011000010100010011 *
1+
b00000000000000000000000000001100 ,
b00000000000000000000000000000000 -
b00000000000000000000000000010000 .
b00000000000000000000000000010000 0
b10110 1
b0010011 2
b000 3
b0000000 4
#63
0#
#64
1#
b00000000000101011000010110010011 *
b00000000000000000000000000010000 ,
b00000000000000000000000000000001 -
b00000000000000000000000000010100 .
b00000000000000000000000000010001 /
b00000000000000000000000000010100 0
#65
0#
#66
1#
0&
1'
0(
1)
b11111110011001011001110011100011 *
0+
b00000000000000000000000000010100 ,
b11111111111111111111111111111000 -
b00000000000000000000000000011000 .
b00000000000000000000000000001100 /
b00000000000000000000000000001100 0
b01001 1
b1100011 2
b001 3
b1111111 4
#67
0#
#68
1#
1&
0'
1(
0)
b00000000000001011000010100010011 *
1+
b00000000000000000000000000001100 ,
b00000000000000000000000000000000 -
b00000000000000000000000000010000 .
b00000000000000000000000000010000 0
b10110 1
b0010011 2
b000 3
b0000000 4
#69
0#
#70
1#
b00000000000101011000010110010011 *
b00000000000000000000000000010000 ,
b00000000000000000000000000000001 -
b00000000000000000000000000010100 .
b00000000000000000000000000010001 /
b00000000000000000000000000010100 0
#71
0#
#72
1#
0&
1'
0(
1)
b11111110011001011001110011100011 *
0+
b00000000000000000000000000010100 ,
b11111111111111111111111111111000 -
b00000000000000000000000000011000 .
b00000000000000000000000000001100 /
b00000000000000000000000000001100 0
b01001 1
b1100011 2
b001 3
b1111111 4
#73
0#
#74
1#
1&
0'
1(
0)
b00000000000001011000010100010011 *
1+
b00000000000000000000000000001100 ,
b00000000000000000000000000000000 -
b00000000000000000000000000010000 .
b00000000000000000000000000010000 0
b10110 1
b0010011 2
b000 3
b0000000 4
#75
0#
#76
1#
b00000000000101011000010110010011 *
b00000000000000000000000000010000 ,
b00000000000000000000000000000001 -
b00000000000000000000000000010100 .
b00000000000000000000000000010001 /
b00000000000000000000000000010100 0
#77
0#
#78
1#
0&
1'
0(
1)
b11111110011001011001110011100011 *
0+
b00000000000000000000000000010100 ,
b11111111111111111111111111111000 -
b00000000000000000000000000011000 .
b00000000000000000000000000001100 /
b00000000000000000000000000001100 0
b01001 1
b1100011 2
b001 3
b1111111 4
#79
0#
#80
1#
1&
0'
1(
0)
b00000000000001011000010100010011 *
1+
b00000000000000000000000000001100 ,
b00000000000000000000000000000000 -
b00000000000000000000000000010000 .
b00000000000000000000000000010000 0
b10110 1
b0010011 2
b000 3
b0000000 4
#81
0#
#82
1#
b00000000000101011000010110010011 *
b00000000000000000000000000010000 ,
b00000000000000000000000000000001 -
b00000000000000000000000000010100 .
b00000000000000000000000000010001 /
b00000000000000000000000000010100 0
#83
0#
#84
1#
0&
1'
0(
1)
b11111110011001011001110011100011 *
0+
b00000000000000000000000000010100 ,
b11111111111111111111111111111000 -
b00000000000000000000000000011000 .
b00000000000000000000000000001100 /
b00000000000000000000000000001100 0
b01001 1
b1100011 2
b001 3
b1111111 4
#85
0#
#86
1#
1&
0'
1(
0)
b00000000000001011000010100010011 *
1+
b00000000000000000000000000001100 ,
b00000000000000000000000000000000 -
b00000000000000000000000000010000 .
b00000000000000000000000000010000 0
b10110 1
b0010011 2
b000 3
b0000000 4
#87
0#
#88
1#
b00000000000101011000010110010011 *
b00000000000000000000000000010000 ,
b00000000000000000000000000000001 -
b00000000000000000000000000010100 .
b00000000000000000000000000010001 /
b00000000000000000000000000010100 0
#89
0#
#90
1#
0&
1'
0(
1)
b11111110011001011001110011100011 *
0+
b00000000000000000000000000010100 ,
b11111111111111111111111111111000 -
b00000000000000000000000000011000 .
b00000000000000000000000000001100 /
b00000000000000000000000000001100 0
b01001 1
b1100011 2
b001 3
b1111111 4
#91
0#
#92
1#
1&
0'
1(
0)
b00000000000001011000010100010011 *
1+
b00000000000000000000000000001100 ,
b00000000000000000000000000000000 -
b00000000000000000000000000010000 .
b00000000000000000000000000010000 0
b10110 1
b0010011 2
b000 3
b0000000 4
#93
0#
#94
1#
b00000000000101011000010110010011 *
b00000000000000000000000000010000 ,
b00000000000000000000000000000001 -
b00000000000000000000000000010100 .
b00000000000000000000000000010001 /
b00000000000000000000000000010100 0
#95
0#
#96
1#
0&
1'
0(
1)
b11111110011001011001110011100011 *
0+
b00000000000000000000000000010100 ,
b11111111111111111111111111111000 -
b00000000000000000000000000011000 .
b00000000000000000000000000001100 /
b00000000000000000000000000001100 0
b01001 1
b1100011 2
b001 3
b1111111 4
#97
0#
#98
1#
1&
0'
1(
0)
b00000000000001011000010100010011 *
1+
b00000000000000000000000000001100 ,
b00000000000000000000000000000000 -
b00000000000000000000000000010000 .
b00000000000000000000000000010000 0
b10110 1
b0010011 2
b000 3
b0000000 4
#99
0#
#100
1#
b00000000000101011000010110010011 *
b00000000000000000000000000010000 ,
b00000000000000000000000000000001 -
b00000000000000000000000000010100 .
b00000000000000000000000000010001 /
b00000000000000000000000000010100 0
#101
0#
#102
1#
0&
1'
0(
1)
b11111110011001011001110011100011 *
0+
b00000000000000000000000000010100 ,
b11111111111111111111111111111000 -
b00000000000000000000000000011000 .
b00000000000000000000000000001100 /
b00000000000000000000000000001100 0
b01001 1
b1100011 2
b001 3
b1111111 4
#103
0#
#104
1#
1&
0'
1(
0)
b00000000000001011000010100010011 *
1+
b00000000000000000000000000001100 ,
b00000000000000000000000000000000 -
b00000000000000000000000000010000 .
b00000000000000000000000000010000 0
b10110 1
b0010011 2
b000 3
b0000000 4
#105
0#
#106
1#
b00000000000101011000010110010011 *
b00000000000000000000000000010000 ,
b00000000000000000000000000000001 -
b00000000000000000000000000010100 .
b00000000000000000000000000010001 /
b00000000000000000000000000010100 0
#107
0#
#108
1#
0&
1'
0(
1)
b11111110011001011001110011100011 *
0+
b00000000000000000000000000010100 ,
b11111111111111111111111111111000 -
b00000000000000000000000000011000 .
b00000000000000000000000000001100 /
b00000000000000000000000000001100 0
b01001 1
b1100011 2
b001 3
b1111111 4
#109
0#
#110
1#
1&
0'
1(
0)
b00000000000001011000010100010011 *
1+
b00000000000000000000000000001100 ,
b00000000000000000000000000000000 -
b00000000000000000000000000010000 .
b00000000000000000000000000010000 0
b10110 1
b0010011 2
b000 3
b0000000 4
#111
0#
#112
1#
b00000000000101011000010110010011 *
b00000000000000000000000000010000 ,
b00000000000000000000000000000001 -
b00000000000000000000000000010100 .
b00000000000000000000000000010001 /
b00000000000000000000000000010100 0
#113
0#
#114
1#
0&
1'
0(
1)
b11111110011001011001110011100011 *
0+
b00000000000000000000000000010100 ,
b11111111111111111111111111111000 -
b00000000000000000000000000011000 .
b00000000000000000000000000001100 /
b00000000000000000000000000001100 0
b01001 1
b1100011 2
b001 3
b1111111 4
#115
0#
#116
1#
1&
0'
1(
0)
b00000000000001011000010100010011 *
1+
b00000000000000000000000000001100 ,
b00000000000000000000000000000000 -
b00000000000000000000000000010000 .
b00000000000000000000000000010000 0
b10110 1
b0010011 2
b000 3
b0000000 4
#117
0#
#118
1#
b00000000000101011000010110010011 *
b00000000000000000000000000010000 ,
b00000000000000000000000000000001 -
b00000000000000000000000000010100 .
b00000000000000000000000000010001 /
b00000000000000000000000000010100 0
#119
0#
#120
1#
0&
1'
0(
1)
b11111110011001011001110011100011 *
0+
b00000000000000000000000000010100 ,
b11111111111111111111111111111000 -
b00000000000000000000000000011000 .
b00000000000000000000000000001100 /
b00000000000000000000000000001100 0
b01001 1
b1100011 2
b001 3
b1111111 4
#121
0#
#122
1#
1&
0'
1(
0)
b00000000000001011000010100010011 *
1+
b00000000000000000000000000001100 ,
b00000000000000000000000000000000 -
b00000000000000000000000000010000 .
b00000000000000000000000000010000 0
b10110 1
b0010011 2
b000 3
b0000000 4
#123
0#
#124
1#
b00000000000101011000010110010011 *
b00000000000000000000000000010000 ,
b00000000000000000000000000000001 -
b00000000000000000000000000010100 .
b00000000000000000000000000010001 /
b00000000000000000000000000010100 0
#125
0#
#126
1#
0&
1'
0(
1)
b11111110011001011001110011100011 *
0+
b00000000000000000000000000010100 ,
b11111111111111111111111111111000 -
b00000000000000000000000000011000 .
b00000000000000000000000000001100 /
b00000000000000000000000000001100 0
b01001 1
b1100011 2
b001 3
b1111111 4
#127
0#
#128
1#
1&
0'
1(
0)
b00000000000001011000010100010011 *
1+
b00000000000000000000000000001100 ,
b00000000000000000000000000000000 -
b00000000000000000000000000010000 .
b00000000000000000000000000010000 0
b10110 1
b0010011 2
b000 3
b0000000 4
#129
0#
#130
1#
b00000000000101011000010110010011 *
b00000000000000000000000000010000 ,
b00000000000000000000000000000001 -
b00000000000000000000000000010100 .
b00000000000000000000000000010001 /
b00000000000000000000000000010100 0
#131
0#
#132
1#
0&
1'
0(
1)
b11111110011001011001110011100011 *
0+
b00000000000000000000000000010100 ,
b11111111111111111111111111111000 -
b00000000000000000000000000011000 .
b00000000000000000000000000001100 /
b00000000000000000000000000001100 0
b01001 1
b1100011 2
b001 3
b1111111 4
#133
0#
#134
1#
1&
0'
1(
0)
b00000000000001011000010100010011 *
1+
b00000000000000000000000000001100 ,
b00000000000000000000000000000000 -
b00000000000000000000000000010000 .
b00000000000000000000000000010000 0
b10110 1
b0010011 2
b000 3
b0000000 4
#135
0#
#136
1#
b00000000000101011000010110010011 *
b00000000000000000000000000010000 ,
b00000000000000000000000000000001 -
b00000000000000000000000000010100 .
b00000000000000000000000000010001 /
b00000000000000000000000000010100 0
#137
0#
#138
1#
0&
1'
0(
1)
b11111110011001011001110011100011 *
0+
b00000000000000000000000000010100 ,
b11111111111111111111111111111000 -
b00000000000000000000000000011000 .
b00000000000000000000000000001100 /
b00000000000000000000000000001100 0
b01001 1
b1100011 2
b001 3
b1111111 4
#139
0#
#140
1#
1&
0'
1(
0)
b00000000000001011000010100010011 *
1+
b00000000000000000000000000001100 ,
b00000000000000000000000000000000 -
b00000000000000000000000000010000 .
b00000000000000000000000000010000 0
b10110 1
b0010011 2
b000 3
b0000000 4
#141
0#
#142
1#
b00000000000101011000010110010011 *
b00000000000000000000000000010000 ,
b00000000000000000000000000000001 -
b00000000000000000000000000010100 .
b00000000000000000000000000010001 /
b00000000000000000000000000010100 0
#143
0#
#144
1#
0&
1'
0(
1)
b11111110011001011001110011100011 *
0+
b00000000000000000000000000010100 ,
b11111111111111111111111111111000 -
b00000000000000000000000000011000 .
b00000000000000000000000000001100 /
b00000000000000000000000000001100 0
b01001 1
b1100011 2
b001 3
b1111111 4
#145
0#
#146
1#
1&
0'
1(
0)
b00000000000001011000010100010011 *
1+
b00000000000000000000000000001100 ,
b00000000000000000000000000000000 -
b00000000000000000000000000010000 .
b00000000000000000000000000010000 0
b10110 1
b0010011 2
b000 3
b0000000 4
#147
0#
#148
1#
b00000000000101011000010110010011 *
b00000000000000000000000000010000 ,
b00000000000000000000000000000001 -
b00000000000000000000000000010100 .
b00000000000000000000000000010001 /
b00000000000000000000000000010100 0
#149
0#
#150
1#
0&
1'
0(
1)
b11111110011001011001110011100011 *
0+
b00000000000000000000000000010100 ,
b11111111111111111111111111111000 -
b00000000000000000000000000011000 .
b00000000000000000000000000001100 /
b00000000000000000000000000001100 0
b01001 1
b1100011 2
b001 3
b1111111 4
#151
0#
#152
1#
1&
0'
1(
0)
b00000000000001011000010100010011 *
1+
b00000000000000000000000000001100 ,
b00000000000000000000000000000000 -
b00000000000000000000000000010000 .
b00000000000000000000000000010000 0
b10110 1
b0010011 2
b000 3
b0000000 4
#153
0#
#154
1#
b00000000000101011000010110010011 *
b00000000000000000000000000010000 ,
b00000000000000000000000000000001 -
b00000000000000000000000000010100 .
b00000000000000000000000000010001 /
b00000000000000000000000000010100 0
#155
0#
#156
1#
0&
1'
0(
1)
b11111110011001011001110011100011 *
0+
b00000000000000000000000000010100 ,
b11111111111111111111111111111000 -
b00000000000000000000000000011000 .
b00000000000000000000000000001100 /
b00000000000000000000000000001100 0
b01001 1
b1100011 2
b001 3
b1111111 4
#157
0#
#158
1#
1&
0'
1(
0)
b00000000000001011000010100010011 *
1+
b00000000000000000000000000001100 ,
b00000000000000000000000000000000 -
b00000000000000000000000000010000 .
b00000000000000000000000000010000 0
b10110 1
b0010011 2
b000 3
b0000000 4
#159
0#
#160
1#
b00000000000101011000010110010011 *
b00000000000000000000000000010000 ,
b00000000000000000000000000000001 -
b00000000000000000000000000010100 .
b00000000000000000000000000010001 /
b00000000000000000000000000010100 0
#161
0#
#162
1#
0&
1'
0(
1)
b11111110011001011001110011100011 *
0+
b00000000000000000000000000010100 ,
b11111111111111111111111111111000 -
b00000000000000000000000000011000 .
b00000000000000000000000000001100 /
b00000000000000000000000000001100 0
b01001 1
b1100011 2
b001 3
b1111111 4
#163
0#
#164
1#
1&
0'
1(
0)
b00000000000001011000010100010011 *
1+
b00000000000000000000000000001100 ,
b00000000000000000000000000000000 -
b00000000000000000000000000010000 .
b00000000000000000000000000010000 0
b10110 1
b0010011 2
b000 3
b0000000 4
#165
0#
#166
1#
b00000000000101011000010110010011 *
b00000000000000000000000000010000 ,
b00000000000000000000000000000001 -
b00000000000000000000000000010100 .
b00000000000000000000000000010001 /
b00000000000000000000000000010100 0
#167
0#
#168
1#
0&
1'
0(
1)
b11111110011001011001110011100011 *
0+
b00000000000000000000000000010100 ,
b11111111111111111111111111111000 -
b00000000000000000000000000011000 .
b00000000000000000000000000001100 /
b00000000000000000000000000001100 0
b01001 1
b1100011 2
b001 3
b1111111 4
#169
0#
#170
1#
1&
0'
1(
0)
b00000000000001011000010100010011 *
1+
b00000000000000000000000000001100 ,
b00000000000000000000000000000000 -
b00000000000000000000000000010000 .
b00000000000000000000000000010000 0
b10110 1
b0010011 2
b000 3
b0000000 4
#171
0#
#172
1#
b00000000000101011000010110010011 *
b00000000000000000000000000010000 ,
b00000000000000000000000000000001 -
b00000000000000000000000000010100 .
b00000000000000000000000000010001 /
b00000000000000000000000000010100 0
#173
0#
#174
1#
0&
1'
0(
1)
b11111110011001011001110011100011 *
0+
b00000000000000000000000000010100 ,
b11111111111111111111111111111000 -
b00000000000000000000000000011000 .
b00000000000000000000000000001100 /
b00000000000000000000000000001100 0
b01001 1
b1100011 2
b001 3
b1111111 4
#175
0#
#176
1#
1&
0'
1(
0)
b00000000000001011000010100010011 *
1+
b00000000000000000000000000001100 ,
b00000000000000000000000000000000 -
b00000000000000000000000000010000 .
b00000000000000000000000000010000 0
b10110 1
b0010011 2
b000 3
b0000000 4
#177
0#
